tensorflowAndKeras/__init__.py
tensorflowAndKeras-0.1.dist-info/METADATA
tensorflowAndKeras-0.1.dist-info/WHEEL
tensorflowAndKeras-0.1.dist-info/top_level.txt
tensorflowAndKeras-0.1.dist-info/RECORD
