Metadata-Version: 2.1
Name: tensorflowAndKeras
Version: 0.1
Summary: Custom SKLearn package by N.K.Bhansodhe
Author: NKBhansodhe
Author-email: mehol25409@farebus.com
